CHANGES.txt
LICENSE.txt
MANIFEST.in
README.rst
setup.py
django_ui_permissions.egg-info/PKG-INFO
django_ui_permissions.egg-info/SOURCES.txt
django_ui_permissions.egg-info/dependency_links.txt
django_ui_permissions.egg-info/top_level.txt
ui_permissions/__init__.py
ui_permissions/forms.py
ui_permissions/models.py
ui_permissions/views.py
ui_permissions/descriptor/__init__.py
ui_permissions/descriptor/permission.py
ui_permissions/descriptor/resource.py
ui_permissions/descriptor/components/__init__.py
ui_permissions/descriptor/components/base.py
ui_permissions/descriptor/components/components.py
ui_permissions/templatetags/__init__.py
ui_permissions/templatetags/ui_permissions_tags.py
ui_permissions/tests/__init__.py
ui_permissions/tests/components.py
ui_permissions/tests/description.py
ui_permissions/tests/resource.py
ui_permissions/tests/validation.py