Metadata-Version: 1.1
Name: django-ui-permissions
Version: 0.3
Summary: Django module that helps manage UI elements using permissions
Home-page: http://bitbucket.org/vadwook/django-ui-permissions/
Author: Piotr Olejarz
Author-email: vadwook@hotmail.com
License: LICENSE.txt
Platform: UNKNOWN
Classifier: Environment :: Web Environment
Classifier: Framework :: Django
Classifier: Intended Audience :: Developers
Classifier: License :: OSI Approved :: MIT License
Classifier: Operating System :: OS Independent
Classifier: Programming Language :: Python :: 2.7
Classifier: Topic :: Internet :: WWW/HTTP
Classifier: Topic :: Internet :: WWW/HTTP :: Dynamic Content
